{
  "type": [
    "h-entry"
  ],
  "properties": {
    "content": [
      "The top articles shared on Twitter from Instapaper, found using the auto-appended text \"(via Instapaper)\"\n"
    ],
    "published": [
      "2012-02-20T21:06:20Z"
    ],
    "entry-type": [
      "bookmark"
    ],
    "name": [
      "(via Instapaper)"
    ],
    "bookmark-of": [
      "http://viainstapaper.com/"
    ],
    "category": [
      "aggregation",
      "instapaper",
      "twitter",
      "via-pinboard"
    ],
    "slug": [
      "via-instapaper"
    ]
  }
}