{
  "type": [
    "h-entry"
  ],
  "properties": {
    "content": [
      "How WordPress.com serves images using S3\n"
    ],
    "published": [
      "2007-10-28T18:18:37Z"
    ],
    "entry-type": [
      "bookmark"
    ],
    "name": [
      "so-you-wanna-see-an-image"
    ],
    "bookmark-of": [
      "http://blog.apokalyptik.com/2007/10/10/so-you-wanna-see-an-image/"
    ],
    "category": [
      "amazon",
      "architecture",
      "s3",
      "scalability",
      "scaling",
      "varnish",
      "web",
      "wordpress",
      "pound",
      "memcached",
      "via-pinboard"
    ],
    "slug": [
      "so-you-wanna-see-an-image"
    ]
  }
}