{
  "type": [
    "h-entry"
  ],
  "properties": {
    "content": [
      "> PostgREST serves a fully RESTful API from any existing PostgreSQL database. It provides a cleaner, more standards-compliant, faster API than you are likely to write from scratch."
    ],
    "published": [
      "2015-01-05T13:33:31Z"
    ],
    "entry-type": [
      "bookmark"
    ],
    "name": [
      "PostgREST"
    ],
    "bookmark-of": [
      "https://github.com/begriffs/postgrest"
    ],
    "category": [
      "postgres",
      "rest",
      "api"
    ],
    "slug": [
      "postgrest"
    ]
  }
}