{
  "type": [
    "h-entry"
  ],
  "properties": {
    "content": [
      "\"More than a quarter of eight to 11-year-olds who are online in the UK have a profile on a social network\"\n"
    ],
    "published": [
      "2008-04-03T12:48:49Z"
    ],
    "entry-type": [
      "bookmark"
    ],
    "name": [
      "Children flock to social networks"
    ],
    "bookmark-of": [
      "http://news.bbc.co.uk/1/hi/technology/7325019.stm"
    ],
    "category": [
      "socialnetworking",
      "children",
      "facebook",
      "bebo",
      "myspace",
      "social",
      "statistics",
      "uk",
      "work",
      "via-pinboard"
    ],
    "slug": [
      "children-flock-to-social-networks"
    ]
  }
}