{
  "type": [
    "h-entry"
  ],
  "properties": {
    "content": [
      "Prevent accidental cmd-q quitting of Chrome (Mac) by going to about:flags and clicking \"Enable\" under \"Confirm to Quit\" http://code.google.com/p/chromium/issues/detail?id=35022#c6"
    ],
    "published": [
      "2011-03-08T07:40:36Z"
    ],
    "entry-type": [
      "note"
    ],
    "category": [
      "via-twitter"
    ],
    "syndication": [
      "https://twitter.com/barryf/status/45026111402409984"
    ],
    "slug": [
      "tweet-45026111402409984"
    ]
  }
}