{
  "type": [
    "h-entry"
  ],
  "properties": {
    "content": [
      "@BenHobson Cheers. Er, I'll have to be careful what I say... Yes, dinner's out tonight, @larrylou100 only cooks supper."
    ],
    "published": [
      "2011-11-21T15:28:32Z"
    ],
    "entry-type": [
      "reply"
    ],
    "in-reply-to": [
      "https://twitter.com/20511088/status/138638323634814977"
    ],
    "category": [
      "via-twitter"
    ],
    "syndication": [
      "https://twitter.com/barryf/status/138639940513824769"
    ],
    "slug": [
      "tweet-138639940513824769"
    ]
  }
}