{
  "type": [
    "h-entry"
  ],
  "properties": {
    "content": [
      "\"Stewart Lee doesn't just tell jokes: he milks them... [cont'd]\" fantastic comment below a Guardian editorial on SL http://www.guardian.co.uk/discussion/comment-permalink/11002309"
    ],
    "published": [
      "2011-06-02T13:43:20Z"
    ],
    "entry-type": [
      "note"
    ],
    "category": [
      "via-twitter"
    ],
    "syndication": [
      "https://twitter.com/barryf/status/76282754903445504"
    ],
    "slug": [
      "tweet-76282754903445504"
    ]
  }
}