{
  "type": [
    "h-entry"
  ],
  "properties": {
    "content": [
      "@thesambarnes I never had the pleasure of working with @jlcoassin but you've nothing to worry about. Enjoy your last day and week of FIFA!"
    ],
    "published": [
      "2011-06-30T21:36:23Z"
    ],
    "entry-type": [
      "reply"
    ],
    "in-reply-to": [
      "https://twitter.com/23260761/status/86543380913463296"
    ],
    "category": [
      "via-twitter"
    ],
    "syndication": [
      "https://twitter.com/barryf/status/86548661957443584"
    ],
    "slug": [
      "tweet-86548661957443584"
    ]
  }
}