{
  "type": [
    "h-entry"
  ],
  "properties": {
    "content": [
      "Detailed description of GitHub's new architecture\n"
    ],
    "published": [
      "2009-10-31T18:27:24Z"
    ],
    "entry-type": [
      "bookmark"
    ],
    "name": [
      "How We Made GitHub Fast"
    ],
    "bookmark-of": [
      "http://github.com/blog/530-how-we-made-github-fast"
    ],
    "category": [
      "rails",
      "unicorn",
      "git",
      "drbd",
      "smoke",
      "haproxy",
      "redis",
      "ernie",
      "bert",
      "rpc",
      "ssh",
      "nginx",
      "via-pinboard"
    ],
    "slug": [
      "how-we-made-github-fast"
    ]
  }
}