{
  "type": [
    "h-entry"
  ],
  "properties": {
    "content": [
      "Javascript effects library\n"
    ],
    "published": [
      "2005-10-27T09:47:00Z"
    ],
    "entry-type": [
      "bookmark"
    ],
    "name": [
      "moo.fx - the next small thing"
    ],
    "bookmark-of": [
      "http://moofx.mad4milk.net/"
    ],
    "category": [
      "web",
      "design",
      "prototype",
      "javascript",
      "via-pinboard"
    ],
    "slug": [
      "moo-fx-the-next-small-thing"
    ]
  }
}